{"subtitle": {"x": -20, "text": "500000 records and 1000000 operations. More is Better."}, "yAxis": {"title": {"text": "RPS"}}, "series": [{"data": [{"y": 3471.286, "x": 1}, {"y": 6169.664, "x": 2}, {"y": 11596.349, "x": 4}, {"y": 19932.932, "x": 8}, {"y": 19527.16, "x": 16}, {"y": 19155.916, "x": 32}, {"y": 28921.463, "x": 64}, {"y": 30763.988, "x": 128}], "type": "line", "name": "MongoDB v2.4"}, {"data": [{"y": 5706.056, "x": 1}, {"y": 10562.674, "x": 2}, {"y": 20182.007, "x": 4}, {"y": 37064.538, "x": 8}, {"y": 60078.99, "x": 16}, {"y": 56427.578, "x": 32}, {"y": 73767.03, "x": 64}, {"y": 53821.444, "x": 128}], "type": "line", "name": "Redis 2.6"}, {"data": [{"y": 6216.894, "x": 1}, {"y": 12479.615, "x": 2}, {"y": 24424.14, "x": 4}, {"y": 43527.277, "x": 8}, {"y": 71355.828, "x": 16}, {"y": 76839.412, "x": 32}, {"y": 63632.867, "x": 64}, {"y": 64811.583, "x": 128}], "type": "line", "name": "Tarantool with TREE index"}, {"data": [{"y": 4585.784, "x": 1}, {"y": 8812.614, "x": 2}, {"y": 14996.888, "x": 4}, {"y": 20936.364, "x": 8}, {"y": 23956.285, "x": 16}, {"y": 26782.37, "x": 32}, {"y": 25780.767, "x": 64}, {"y": 26819.413, "x": 128}], "type": "line", "name": "Tarantool with HASH index"}, {"data": [{"y": 4196.087, "x": 1}, {"y": 7782.309, "x": 2}, {"y": 14683.172, "x": 4}, {"y": 24352.724, "x": 8}, {"y": 29403.811, "x": 16}, {"y": 29581.583, "x": 32}, {"y": 38261.301, "x": 64}, {"y": 37654.928, "x": 128}], "type": "line", "name": "TokuMX 1.0"}], "title": {"x": -20, "text": "Throughput"}, "chart": {}, "tooltip": {"formatter": "return this.series.name + '<br/>' + this.x + ' clients : ' + this.y + ' RPS'"}, "credits": {"enabled": false}, "xAxis": {"allowDecimals": false, "title": {"text": "Clients"}}, "legend": {}}